README.rst
setup.py
nbthread_spark/__init__.py
nbthread_spark/manager.py
nbthread_spark/spark.py
nbthread_spark/stream.py
nbthread_spark.egg-info/PKG-INFO
nbthread_spark.egg-info/SOURCES.txt
nbthread_spark.egg-info/dependency_links.txt
nbthread_spark.egg-info/requires.txt
nbthread_spark.egg-info/top_level.txt