Metadata-Version: 1.0
Name: nbthread-spark
Version: 0.0.6
Summary: Spark Structured Streaming multithread in IPython Notebooks
Home-page: UNKNOWN
Author: Data Bootcamp
Author-email: contato@databootcamp.com.br
License: Apache
Platform: UNKNOWN
